PeeweeMethods/__init__.py
PeeweeMethods/main.py
PeeweeMethods-0.0.1.dist-info/License
PeeweeMethods-0.0.1.dist-info/METADATA
PeeweeMethods-0.0.1.dist-info/WHEEL
PeeweeMethods-0.0.1.dist-info/top_level.txt
PeeweeMethods-0.0.1.dist-info/RECORD
